ton_node_control/__init__.py
ton_node_control/cli/__init__.py
ton_node_control/cli/system.py
ton_node_control/cli/utils/__init__.py
ton_node_control/cli/utils/file_read.py
ton_node_control/cli/utils/messages.py
ton_node_control/utils/__init__.py
ton_node_control/utils/typing.py
ton_node_control-0.0.1.1.dist-info/LICENSE
ton_node_control-0.0.1.1.dist-info/WHEEL
ton_node_control-0.0.1.1.dist-info/METADATA
ton_node_control-0.0.1.1.dist-info/RECORD
