Metadata-Version: 2.1
Name: ton-node-control
Version: 0.0.1.1
Summary: 
Home-page: https://github.com/Walther-s-Engineering/ton-node-control
License: Apache-2.0
Keywords: The Open Network,TON,blockhain,tools
Author: Alexander Walther
Author-email: asushofman@gmail.com
Requires-Python: >=3.10,<4.0
Classifier: Development Status :: 1 - Planning
Classifier: Environment :: Console
Classifier: License :: OSI Approved :: Apache Software License
Classifier: Operating System :: POSIX :: Linux
Classifier: Programming Language :: Python :: 3
Classifier: Programming Language :: Python :: 3.10
Classifier: Programming Language :: Python :: 3.8
Classifier: Programming Language :: Python :: 3.9
Classifier: Topic :: Software Development :: User Interfaces
Classifier: Topic :: System :: Distributed Computing
Classifier: Topic :: System :: Networking
Classifier: Topic :: System :: Networking :: Monitoring
Classifier: Topic :: Utilities
Requires-Dist: PyYAML (==6.0)
Requires-Dist: click (==8.1.3)
Requires-Dist: mypy (==0.982)
Requires-Dist: pytest (==7.2.0)
Requires-Dist: toml (==0.10.2)
Project-URL: Repository, https://github.com/Walther-s-Engineering/ton-node-control.git
